setup.py
latr/__init__.py
latr/batches.py
latr/core.py
latr.egg-info/PKG-INFO
latr.egg-info/SOURCES.txt
latr.egg-info/dependency_links.txt
latr.egg-info/top_level.txt