Metadata-Version: 1.0
Name: latr
Version: 0.1.2
Summary: Lazy Iterator Chains
Home-page: UNKNOWN
Author: Brian Lauber
Author-email: constructible.truth@gmail.com
License: UNKNOWN
Platform: UNKNOWN
